__init__.py
quickstart.py
termical_lib/__init__.py
termical_lib/__main__.py
termical_lib/authentication.py
termical_lib/termical.py
termical_lib/termicalFunctions.py
Termical-0.4.dist-info/LICENSE
Termical-0.4.dist-info/METADATA
Termical-0.4.dist-info/WHEEL
Termical-0.4.dist-info/entry_points.txt
Termical-0.4.dist-info/top_level.txt
Termical-0.4.dist-info/RECORD
