Metadata-Version: 2.1
Name: Termical
Version: 0.4
Summary: Simple terminal-based calendar
Home-page: UNKNOWN
Author: Marek Kužel
Author-email: marekuzel1@gmail.com
License: UNKNOWN
Platform: UNKNOWN
License-File: LICENSE
Requires-Dist: google-api-python-client
Requires-Dist: google-auth-httplib2
Requires-Dist: google-auth-oauthlib
Requires-Dist: pytz
